customer_segmentation_clustering/__init__.py
customer_segmentation_clustering/cluster_scoring.py
customer_segmentation_clustering/data_preprocessing.py
customer_segmentation_clustering/feature_engineering.py
customer_segmentation_clustering/main.py
Cust_segmentation-0.0.0.dist-info/LICENSE
Cust_segmentation-0.0.0.dist-info/METADATA
Cust_segmentation-0.0.0.dist-info/WHEEL
Cust_segmentation-0.0.0.dist-info/top_level.txt
Cust_segmentation-0.0.0.dist-info/RECORD
