Metadata-Version: 2.1
Name: Cust_segmentation
Version: 0.0.0
Summary: A customer segmentation package for preprocessing data
Home-page: 
Author: Phalguni
Author-email: phalgunishenoy2002@gmail.com
Classifier: Programming Language :: Python :: 3
Classifier: License :: OSI Approved :: MIT License
Classifier: Operating System :: OS Independent
Requires-Python: >=3.6
License-File: LICENSE
